AUTHORS
COPYING
MANIFEST.in
README
build.sh
ez_setup.py
gen-doc-api.sh
setup.cfg
setup.py
ecore/__init__.py
ecore/ecore.c_ecore.c
ecore/ecore.c_ecore.h
ecore/ecore.c_ecore.pyx
ecore/ecore.c_ecore_animator.pxi
ecore/ecore.c_ecore_events.pxi
ecore/ecore.c_ecore_exe.pxi
ecore/ecore.c_ecore_fd_handler.pxi
ecore/ecore.c_ecore_idle_enterer.pxi
ecore/ecore.c_ecore_idle_exiter.pxi
ecore/ecore.c_ecore_idler.pxi
ecore/ecore.c_ecore_timer.pxi
ecore/evas/__init__.py
ecore/evas/ecore.evas.c_ecore_evas.c
ecore/evas/ecore.evas.c_ecore_evas.pyx
ecore/evas/ecore.evas.c_ecore_evas_base.pxi
ecore/evas/ecore.evas.c_ecore_evas_base_x11.pxi
ecore/evas/ecore.evas.c_ecore_evas_buffer.pxi
ecore/evas/ecore.evas.c_ecore_evas_directfb.pxi
ecore/evas/ecore.evas.c_ecore_evas_fb.pxi
ecore/evas/ecore.evas.c_ecore_evas_gl_x11.pxi
ecore/evas/ecore.evas.c_ecore_evas_software_x11.pxi
ecore/evas/ecore.evas.c_ecore_evas_software_x11_16.pxi
ecore/evas/ecore.evas.c_ecore_evas_xrender_x11.pxi
ecore/evas/utils.py
ecore/imf/__init__.py
ecore/imf/ecore.imf.c_ecore_imf.c
ecore/imf/ecore.imf.c_ecore_imf.pyx
ecore/win32/__init__.py
ecore/win32/ecore.win32.c_ecore_win32.pyx
ecore/win32/ecore.win32.c_ecore_win32_window.pxi
ecore/x/__init__.py
ecore/x/ecore.x.c_ecore_x.c
ecore/x/ecore.x.c_ecore_x.pyx
ecore/x/ecore.x.c_ecore_x_events.pxi
ecore/x/ecore.x.c_ecore_x_window.pxi
ecore/x/ecore.x.screensaver.c
ecore/x/ecore.x.screensaver.pyx
examples/01-timers.py
examples/02-animators.py
examples/ecore_evas/00-empty.py
examples/ecore_evas/01-empty-resizable.py
examples/ecore_evas/02-centered-rectangle.py
examples/ecore_evas/03-image.py
examples/ecore_evas/04-animation-moving.py
examples/ecore_evas/05-new.py
examples/ecore_evas/icon.png
examples/x/mplayer_embed.py
examples/x/window_creation.py
include/ecore/__init__.py
include/ecore/c_ecore.pxd
include/ecore/evas/__init__.py
include/ecore/evas/c_ecore_evas.pxd
include/ecore/imf/__init__.py
include/ecore/imf/c_ecore_imf.pxd
include/ecore/win32/__init__.py
python_ecore.egg-info/PKG-INFO
python_ecore.egg-info/SOURCES.txt
python_ecore.egg-info/dependency_links.txt
python_ecore.egg-info/not-zip-safe
python_ecore.egg-info/requires.txt
python_ecore.egg-info/top_level.txt
